vkbottle/__init__.py
vkbottle/api/__init__.py
vkbottle/api/abc.py
vkbottle/api/api.py
vkbottle/api/request_rescheduler/__init__.py
vkbottle/api/request_rescheduler/abc.py
vkbottle/api/request_rescheduler/blocking.py
vkbottle/api/request_validator/__init__.py
vkbottle/api/request_validator/abc.py
vkbottle/api/request_validator/translate_friendly_types_validator.py
vkbottle/api/response_validator/__init__.py
vkbottle/api/response_validator/abc.py
vkbottle/api/response_validator/json_validator.py
vkbottle/api/response_validator/vk_api_error_validator.py
vkbottle/api/token_generator/__init__.py
vkbottle/api/token_generator/abc.py
vkbottle/api/token_generator/consistent.py
vkbottle/api/token_generator/single.py
vkbottle/api/token_generator/util.py
vkbottle/bot.py
vkbottle/callback/__init__.py
vkbottle/callback/abc.py
vkbottle/callback/bot_callback.py
vkbottle/dispatch/__init__.py
vkbottle/dispatch/abc.py
vkbottle/dispatch/base.py
vkbottle/dispatch/dispenser/__init__.py
vkbottle/dispatch/dispenser/abc.py
vkbottle/dispatch/dispenser/base.py
vkbottle/dispatch/dispenser/builtin.py
vkbottle/dispatch/handlers/__init__.py
vkbottle/dispatch/handlers/abc.py
vkbottle/dispatch/handlers/from_func_handler.py
vkbottle/dispatch/middlewares/__init__.py
vkbottle/dispatch/middlewares/abc.py
vkbottle/dispatch/return_manager/__init__.py
vkbottle/dispatch/return_manager/abc.py
vkbottle/dispatch/return_manager/bot/__init__.py
vkbottle/dispatch/return_manager/bot/message.py
vkbottle/dispatch/return_manager/user/__init__.py
vkbottle/dispatch/return_manager/user/message.py
vkbottle/dispatch/rules/__init__.py
vkbottle/dispatch/rules/abc.py
vkbottle/dispatch/rules/base.py
vkbottle/dispatch/views/__init__.py
vkbottle/dispatch/views/abc/__init__.py
vkbottle/dispatch/views/abc/dispense.py
vkbottle/dispatch/views/abc/message.py
vkbottle/dispatch/views/abc/raw.py
vkbottle/dispatch/views/abc/view.py
vkbottle/dispatch/views/bot/__init__.py
vkbottle/dispatch/views/bot/message.py
vkbottle_vkru-4.3.12.2.dist-info/METADATA
vkbottle_vkru-4.3.12.2.dist-info/WHEEL
vkbottle_vkru-4.3.12.2.dist-info/licenses/LICENSE
vkbottle_vkru-4.3.12.2.dist-info/RECORD
