Metadata-Version: 2.4
Name: vkbottle-vkru
Version: 4.3.12.2
Summary: Homogenic! Customizable asynchronous VK API framework implementing comfort and speed
License: MIT
License-File: LICENSE
Keywords: vk,vk-api,vkbottle,user-longpoll,async,asyncio,bot,longpoll-api,callback,middleware
Author: timoniq
Maintainer: FeeeeK
Requires-Python: >=3.7.2,<4.0.0
Classifier: Environment :: Console
Classifier: Intended Audience :: Developers
Classifier: License :: OSI Approved :: MIT License
Classifier: Programming Language :: Python :: 3
Classifier: Programming Language :: Python :: 3.8
Classifier: Programming Language :: Python :: 3.9
Classifier: Programming Language :: Python :: 3.10
Classifier: Programming Language :: Python :: 3.11
Classifier: Programming Language :: Python :: 3.12
Classifier: Programming Language :: Python :: 3.13
Classifier: Programming Language :: Python :: 3.14
Classifier: Programming Language :: Python :: 3.7
Classifier: Topic :: Software Development :: Libraries :: Python Modules
Classifier: Topic :: Software Development :: Quality Assurance
Classifier: Typing :: Typed
Requires-Dist: aiofiles (>=0.8,<22.2)
Requires-Dist: aiohttp (>=3.8.1,<4.0.0)
Requires-Dist: choicelib (>=0.1.5,<0.2.0)
Requires-Dist: pydantic (>=1.9.1,<2.0.0)
Requires-Dist: typing-extensions (>=4.3.0,<5.0.0)
Requires-Dist: vbml (>=1.1.post1,<2.0)
Requires-Dist: vkbottle-types-vkru (>=5.131.146.16.2,<6.0.0.0.0)
Requires-Dist: watchfiles (>=0.15,<0.19)
Project-URL: Bug Tracker, https://github.com/Hoyper/vkbottle/issues
Project-URL: Homepage, https://github.com/Hoyper/vkbottle
Project-URL: Repository, https://github.com/Hoyper/vkbottle
